mudkip/__init__.py
mudkip/__main__.py
mudkip/_static/mudkip_furo.css
mudkip/application.py
mudkip/cli.py
mudkip/config.py
mudkip/errors.py
mudkip/extension.py
mudkip/github.py
mudkip/jupyter.py
mudkip/npm.py
mudkip/preset.py
mudkip/server.py
mudkip/vitepress.py
mudkip/watch.py
mudkip-0.8.0.dist-info/entry_points.txt
mudkip-0.8.0.dist-info/LICENSE
mudkip-0.8.0.dist-info/WHEEL
mudkip-0.8.0.dist-info/METADATA
mudkip-0.8.0.dist-info/RECORD
