Metadata-Version: 2.1
Name: mudkip
Version: 0.8.0
Summary: A friendly Sphinx wrapper
Home-page: https://github.com/vberlier/mudkip
License: MIT
Keywords: documentation,sphinx,jupyter-notebooks,autodoc,doctests
Author: Valentin Berlier
Author-email: berlier.v@gmail.com
Requires-Python: >=3.8,<4.0
Classifier: License :: OSI Approved :: MIT License
Classifier: Programming Language :: Python :: 3
Classifier: Programming Language :: Python :: 3.8
Classifier: Programming Language :: Python :: 3.9
Requires-Dist: Sphinx (>=5.1.1,<6.0.0)
Requires-Dist: click (>=8.1.3,<9.0.0)
Requires-Dist: colorama; sys_platform == "win32"
Requires-Dist: furo (>=2022.6.21,<2023.0.0)
Requires-Dist: jupyter-nbextensions-configurator (>=0.5.0,<0.6.0)
Requires-Dist: livereload (>=2.6.3,<3.0.0)
Requires-Dist: myst-nb (>=0.16.0,<0.17.0)
Requires-Dist: notebook (>=6.4.12,<7.0.0)
Requires-Dist: pydata-sphinx-theme (>=0.9.0,<0.10.0)
Requires-Dist: sphinx-rtd-theme (>=1.0.0,<2.0.0)
Requires-Dist: sphinxcontrib-mermaid (>=0.7.1,<0.8.0)
Requires-Dist: tomlkit (>=0.7.0)
Requires-Dist: watchdog (>=2.1.9,<3.0.0)
Project-URL: Documentation, https://github.com/vberlier/mudkip
Project-URL: Repository, https://github.com/vberlier/mudkip
